[
  {
    "se": "S01E01",
    "title": "Where's Josie?",
    "tt": 1277294,
    "air_date": "1972-09-09",
    "description": null,
    "cast": null
  },
  {
    "se": "S01E02",
    "title": "Make Way for the Multi-men",
    "tt": 1277282,
    "air_date": "1972-09-16",
    "description": null,
    "cast": null
  },
  {
    "se": "S01E03",
    "title": "The Sleeping Planet",
    "tt": 1277289,
    "air_date": "1972-09-23",
    "description": null,
    "cast": null
  },
  {
    "se": "S01E04",
    "title": "Alien Alan",
    "tt": 1277279,
    "air_date": "1972-09-30",
    "description": null,
    "cast": null
  },
  {
    "se": "S01E05",
    "title": "The Water Planet",
    "tt": 1277292,
    "air_date": "1972-10-07",
    "description": null,
    "cast": null
  },
  {
    "se": "S01E06",
    "title": "The Sun Haters",
    "tt": 1277291,
    "air_date": "1972-10-14",
    "description": null,
    "cast": null
  },
  {
    "se": "S01E07",
    "title": "The Mini-man Menace",
    "tt": 1277288,
    "air_date": "1972-10-21",
    "description": null,
    "cast": null
  },
  {
    "se": "S01E08",
    "title": "The Space Pirates",
    "tt": 1277290,
    "air_date": "1972-10-28",
    "description": null,
    "cast": null
  },
  {
    "se": "S01E09",
    "title": "Anything You Can Zoo",
    "tt": 1277281,
    "air_date": "1972-11-04",
    "description": null,
    "cast": null
  },
  {
    "se": "S01E10",
    "title": "Now You See Them, Now You Don't",
    "tt": 1277283,
    "air_date": "1972-11-11",
    "description": null,
    "cast": null
  },
  {
    "se": "S01E11",
    "title": "The Four-eyed Dragon of Cygnon",
    "tt": 1277286,
    "air_date": "1972-11-18",
    "description": null,
    "cast": null
  },
  {
    "se": "S01E12",
    "title": "The Forward Backward People of Xarock",
    "tt": 1277285,
    "air_date": "1972-11-25",
    "description": null,
    "cast": null
  },
  {
    "se": "S01E13",
    "title": "The Hollow Planet",
    "tt": 1277287,
    "air_date": "1972-12-02",
    "description": null,
    "cast": null
  },
  {
    "se": "S01E14",
    "title": "All Hail Goddess Melody",
    "tt": 1277280,
    "air_date": "1972-12-09",
    "description": null,
    "cast": null
  },
  {
    "se": "S01E15",
    "title": "Outer Space Ark",
    "tt": 1277284,
    "air_date": "1972-12-16",
    "description": null,
    "cast": null
  },
  {
    "se": "S01E16",
    "title": "Warrior Women of Amazonia",
    "tt": 1277293,
    "air_date": "1972-12-30",
    "description": null,
    "cast": null
  }
]
