[
  {
    "se": "S01E01",
    "title": "The Big Ripoff",
    "tt": 644850,
    "air_date": "1975-03-11",
    "description": null,
    "cast": [
      {
        "name": "Tony Curtis",
        "nm": 348,
        "roles": [
          {
            "char": "McCoy",
            "ch": 86308
          }
        ]
      },
      {
        "name": "John Dehner",
        "nm": 215000,
        "roles": [
          {
            "char": "Bishop"
          }
        ]
      },
      {
        "name": "Linda Evans",
        "nm": 2067,
        "roles": [

        ]
      },
      {
        "name": "Larry Hagman",
        "nm": 1306,
        "roles": [
          {
            "char": "Darnell"
          }
        ]
      },
      {
        "name": "Brenda Vaccaro",
        "nm": 882853,
        "roles": [
          {
            "char": "Brenda"
          }
        ]
      },
      {
        "name": "Morgan Woodward",
        "nm": 940971,
        "roles": [
          {
            "char": "Kelso"
          }
        ]
      }
    ]
  },
  {
    "se": "S01E02",
    "title": "Bless the Big Fish",
    "tt": 644848,
    "air_date": "1975-10-05",
    "description": "F. Morgan Russell, a crafty financial adviser, manages to persuade Papa Leone that he could, thanks to his wise advice, triple the value of the shares he owns, worth 450,000 dollars. Some time later, Papa Leone learns his misfortune: he is ruined. In desperation, he tries to commit suicide. It is then time for McCoy to intervene. He works out a plan to recover the money...",
    "cast": [
      {
        "name": "Philip Bruns",
        "nm": 116575,
        "roles": [
          {
            "char": "Lieutenant Potter"
          }
        ]
      },
      {
        "name": "James V. Christy",
        "nm": 160696,
        "roles": [
          {
            "char": "Cuttman"
          }
        ]
      },
      {
        "name": "Tony Curtis",
        "nm": 348,
        "roles": [
          {
            "char": "McCoy",
            "ch": 86308
          }
        ]
      },
      {
        "name": "Bob Dishy",
        "nm": 228336,
        "roles": [
          {
            "char": "F. Morgan Russell"
          }
        ]
      },
      {
        "name": "David Doyle",
        "nm": 236329,
        "roles": [
          {
            "char": "Dr. Bernheim"
          }
        ]
      },
      {
        "name": "Richard Dysart",
        "nm": 246004,
        "roles": [
          {
            "char": "Boylin"
          }
        ]
      },
      {
        "name": "Hector Elias",
        "nm": 253476,
        "roles": [
          {
            "char": "Pancho Rocha"
          }
        ]
      },
      {
        "name": "Ned Glass",
        "nm": 321982,
        "roles": [
          {
            "char": "Schwartz"
          }
        ]
      },
      {
        "name": "James Gregory",
        "nm": 339834,
        "roles": [
          {
            "char": "Admiral Stemlock"
          }
        ]
      },
      {
        "name": "Guy Marks",
        "nm": 548840,
        "roles": [
          {
            "char": "Mickie"
          }
        ]
      },
      {
        "name": "John McGiver",
        "nm": 569410,
        "roles": [
          {
            "char": "Brookside"
          }
        ]
      },
      {
        "name": "Vito Scotti",
        "nm": 780005,
        "roles": [
          {
            "char": "Papa Leone"
          }
        ]
      }
    ]
  },
  {
    "se": "S01E03",
    "title": "Double Take",
    "tt": 79071,
    "air_date": "1975-11-30",
    "description": null,
    "cast": [
      {
        "name": "Val Avery",
        "nm": 43088,
        "roles": [
          {
            "char": "Turk"
          }
        ]
      },
      {
        "name": "Roscoe Lee Browne",
        "nm": 1975,
        "roles": [
          {
            "char": "Gideon Gibbs"
          }
        ]
      },
      {
        "name": "Philip Chapin",
        "nm": 1510055,
        "roles": [
          {
            "char": "Bruce Connor",
            "ch": 119255
          }
        ]
      },
      {
        "name": "Jackie Coogan",
        "nm": 1067,
        "roles": [
          {
            "char": "Skippy",
            "ch": 334471
          }
        ]
      },
      {
        "name": "Tony Curtis",
        "nm": 348,
        "roles": [
          {
            "char": "McCoy",
            "ch": 86308
          }
        ]
      },
      {
        "name": "Harry Guardino",
        "nm": 345340,
        "roles": [
          {
            "char": "Burt Mather"
          }
        ]
      },
      {
        "name": "J.S. Johnson",
        "nm": 425269,
        "roles": [
          {
            "char": "Finny"
          }
        ]
      },
      {
        "name": "Fiona Lewis",
        "nm": 507187,
        "roles": [
          {
            "char": "Sheila"
          }
        ]
      },
      {
        "name": "Bob Minor",
        "nm": 591567,
        "roles": [
          {
            "char": "Matt"
          }
        ]
      },
      {
        "name": "Jack Paar",
        "nm": 2859595,
        "roles": [
          {
            "char": "Boy"
          }
        ]
      },
      {
        "name": "Paul Picerni",
        "nm": 681608,
        "roles": [
          {
            "char": "Glen Phillips"
          }
        ]
      },
      {
        "name": "Nita Talbot",
        "nm": 847953,
        "roles": [
          {
            "char": "Janice"
          }
        ]
      },
      {
        "name": "Wayne Taylor",
        "nm": 853326,
        "roles": [
          {
            "char": "Fowler"
          }
        ]
      }
    ]
  },
  {
    "se": "S01E04",
    "title": "In Again Out Again",
    "tt": 1163563,
    "air_date": "1976-01-04",
    "description": "Bob Mayfield, a retired gold digger, is on the verge of death and J. Carter Sloan takes advantage of his condition to force him to make a 200,000 dollar life insurance contract. This policy affects the interests of Laura, Bob's sister. Laura confides in Brenda Brooks, a journalist, who manages to persuade McCoy to help Laura recover her heritage...",
    "cast": [
      {
        "name": "Roscoe Lee Browne",
        "nm": 1975,
        "roles": [
          {
            "char": "Gideon Gibbs"
          }
        ]
      },
      {
        "name": "Jack Colvin",
        "nm": 173438,
        "roles": [
          {
            "char": "Hugo"
          }
        ]
      },
      {
        "name": "Elisha Cook Jr.",
        "nm": 176879,
        "roles": [
          {
            "char": "Bob Mayfield"
          }
        ]
      },
      {
        "name": "Tony Curtis",
        "nm": 348,
        "roles": [
          {
            "char": "McCoy",
            "ch": 86308
          }
        ]
      },
      {
        "name": "Liam Dunn",
        "nm": 242668,
        "roles": [
          {
            "char": "Billy Sunshine"
          }
        ]
      },
      {
        "name": "Allen Garfield",
        "nm": 307255,
        "roles": [
          {
            "char": "J. Carter Sloan"
          }
        ]
      },
      {
        "name": "Mark Gordon",
        "nm": 330427,
        "roles": [
          {
            "char": "E. J. Karnes"
          }
        ]
      },
      {
        "name": "Lucille Meredith",
        "nm": 580612,
        "roles": [
          {
            "char": "Lucy"
          }
        ]
      },
      {
        "name": "Bernadette Peters",
        "nm": 1613,
        "roles": [
          {
            "char": "Brenda Brooks"
          }
        ]
      },
      {
        "name": "Natalie Schafer",
        "nm": 769791,
        "roles": [
          {
            "char": "Laura Mayfield"
          }
        ]
      },
      {
        "name": "Mills Watson",
        "nm": 914806,
        "roles": [
          {
            "char": "Sheriff Strong"
          }
        ]
      },
      {
        "name": "Darrell Zwerling",
        "nm": 959022,
        "roles": [
          {
            "char": "Phelps"
          }
        ]
      }
    ]
  },
  {
    "se": "S01E05",
    "title": "New Dollar Day",
    "tt": 1167183,
    "air_date": "1976-01-25",
    "description": null,
    "cast": [
      {
        "name": "Joanna Cassidy",
        "nm": 1026,
        "roles": [

        ]
      },
      {
        "name": "Philip Chapin",
        "nm": 1510055,
        "roles": [
          {
            "char": "Bruce Connor",
            "ch": 119255
          }
        ]
      },
      {
        "name": "Eric Christmas",
        "nm": 160452,
        "roles": [
          {
            "char": "Father Harrigan"
          }
        ]
      },
      {
        "name": "Tony Curtis",
        "nm": 348,
        "roles": [
          {
            "char": "McCoy",
            "ch": 86308
          }
        ]
      },
      {
        "name": "Brenda Scott",
        "nm": 778906,
        "roles": [
          {
            "char": "Teller"
          }
        ]
      },
      {
        "name": "Robert Webber",
        "nm": 916434,
        "roles": [
          {
            "char": "Rogers"
          }
        ]
      }
    ]
  }
]
